pyobs/__init__.py
pyobs/application.py
pyobs/background_task.py
pyobs/environment.py
pyobs/object.py
pyobs/py.typed
pyobs/version.py
pyobs/cli/__init__.py
pyobs/cli/_cli.py
pyobs/cli/pyobs.py
pyobs/cli/pyobsd.py
pyobs/cli/pyobsw.py
pyobs/comm/__init__.py
pyobs/comm/comm.py
pyobs/comm/commlogging.py
pyobs/comm/proxy.py
pyobs/comm/dbus/__init__.py
pyobs/comm/dbus/dbuscomm.py
pyobs/comm/dbus/patch.py
pyobs/comm/dummy/__init__.py
pyobs/comm/dummy/dummycomm.py
pyobs/comm/local/__init__.py
pyobs/comm/local/localcomm.py
pyobs/comm/local/localnetwork.py
pyobs/comm/mock/__init__.py
pyobs/comm/mock/mockcomm.py
pyobs/comm/xmpp/__init__.py
pyobs/comm/xmpp/rpc.py
pyobs/comm/xmpp/xmppclient.py
pyobs/comm/xmpp/xmppcomm.py
pyobs/comm/xmpp/xep_0009/__init__.py
pyobs/comm/xmpp/xep_0009/binding.py
pyobs/comm/xmpp/xep_0009/rpc.py
pyobs/comm/xmpp/xep_0009_timeout/__init__.py
pyobs/comm/xmpp/xep_0009_timeout/rpc.py
pyobs/comm/xmpp/xep_0009_timeout/stanza/RPC.py
pyobs/comm/xmpp/xep_0009_timeout/stanza/__init__.py
pyobs/events/__init__.py
pyobs/events/badweather.py
pyobs/events/event.py
pyobs/events/exposurestatuschanged.py
pyobs/events/filterchanged.py
pyobs/events/focusfound.py
pyobs/events/goodweather.py
pyobs/events/log.py
pyobs/events/modechanged.py
pyobs/events/moduleclosed.py
pyobs/events/moduleopened.py
pyobs/events/motionstatuschanged.py
pyobs/events/move.py
pyobs/events/newimage.py
pyobs/events/newspectrum.py
pyobs/events/offsets.py
pyobs/events/roofclosing.py
pyobs/events/roofopened.py
pyobs/events/taskfailed.py
pyobs/events/taskfinished.py
pyobs/events/taskstarted.py
pyobs/events/testevent.py
pyobs/images/__init__.py
pyobs/images/image.py
pyobs/images/processor.py
pyobs/images/meta/__init__.py
pyobs/images/meta/altazoffsets.py
pyobs/images/meta/exptime.py
pyobs/images/meta/genericoffset.py
pyobs/images/meta/onskydistance.py
pyobs/images/meta/pixeloffsets.py
pyobs/images/meta/radecoffsets.py
pyobs/images/meta/skyoffsets.py
pyobs/images/processors/__init__.py
pyobs_core-1.39.4.dist-info/METADATA
pyobs_core-1.39.4.dist-info/WHEEL
pyobs_core-1.39.4.dist-info/entry_points.txt
pyobs_core-1.39.4.dist-info/licenses/LICENSE
pyobs_core-1.39.4.dist-info/RECORD
