Metadata-Version: 2.4
Name: pyobs-core
Version: 1.39.4
Summary: robotic telescope software
Author-email: Tim-Oliver Husser <thusser@uni-goettingen.de>
License-Expression: MIT
License-File: LICENSE
Requires-Python: >=3.11
Requires-Dist: aiohttp<4,>=3.11.18
Requires-Dist: astroplan<0.11,>=0.10.1
Requires-Dist: astropy<8,>=7.0.1
Requires-Dist: astropydantic>=0.0.5
Requires-Dist: astroquery<0.5,>=0.4.10
Requires-Dist: colour<0.2,>=0.1.5
Requires-Dist: dacite>=1.9.2
Requires-Dist: dbus-next<0.3,>=0.2.3
Requires-Dist: influxdb-client>=1.49.0
Requires-Dist: numpy<3,>=2.2.5
Requires-Dist: pandas>=2.2.3
Requires-Dist: paramiko>=3.5.1
Requires-Dist: py-expression-eval<0.4,>=0.3.14
Requires-Dist: pydantic>=2.12.5
Requires-Dist: pytz~=2025.2
Requires-Dist: pyyaml<7,>=6.0.2
Requires-Dist: requests<3,>=2.32.3
Requires-Dist: scipy<2,>=1.15.2
Requires-Dist: single-source<0.5,>=0.4.0
Requires-Dist: slixmpp==1.8.4
Requires-Dist: typing-extensions<5,>=4.13.2
Provides-Extra: full
Requires-Dist: asyncinotify<5,>=4.2.1; extra == 'full'
Requires-Dist: ccdproc<3,>=2.4.3; extra == 'full'
Requires-Dist: lmfit<2,>=1.3.3; extra == 'full'
Requires-Dist: matrix-nio>=0.25.2; extra == 'full'
Requires-Dist: opencv-python-headless>=4.10.0.84; extra == 'full'
Requires-Dist: photutils<3,>=2.2.0; extra == 'full'
Requires-Dist: pillow>=11.3.0; extra == 'full'
Requires-Dist: python-daemon<4,>=3.1.2; extra == 'full'
Requires-Dist: python-telegram-bot~=22.0; extra == 'full'
Requires-Dist: sep<2,>=1.4.1; (sys_platform == 'linux') and extra == 'full'
Requires-Dist: sunpy>=7.0.1; extra == 'full'
Requires-Dist: tornado<7,>=6.4.2; extra == 'full'
